magiccionary/__init__.py
magiccionary/magic.py
magiccionary-0.1.4.dist-info/METADATA
magiccionary-0.1.4.dist-info/WHEEL
magiccionary-0.1.4.dist-info/top_level.txt
magiccionary-0.1.4.dist-info/RECORD
