Metadata-Version: 2.1
Name: magiccionary
Version: 0.1.4
Summary: Add your description here
Requires-Python: >=3.10
